Pipeline_files/multiplier.v
module multiplier(clk,reset,mul,a,b,done,working,result);

	input clk,reset,mul;
	input [0:31] a,b;
	output done,working;
	output [0:63] result;
	

	wire [0:15] a_h,a_l,b_h,b_l;
	
	assign a_h = a[0:15];
	assign a_l = a[16:31];
	assign b_h = b[0:15];
	assign b_l = b[16:31];
	//state encoding
	localparam STATE_Initial = 3'd0,
				STATE_1 = 3'd1,
				STATE_2 = 3'd2,
				STATE_3 = 3'd3,
				STATE_4 = 3'd4,
				STATE_5 = 3'd5,
				STATE_6 = 3'd6,
				STATE_7 = 3'd7;
	
	reg [0:2] CurrentState,NextState;
	
	reg [0:31] H,L,Z,P; 
	reg [0:63] result;
	reg working,done;
	
	//synchronous state transition
	always @ (posedge clk) begin
		if (reset)  
			CurrentState <= STATE_Initial;
		else 
			CurrentState <= NextState;
	end

	always @ (*) begin
		if (reset) begin
			result <= 0;
			H <= 0;
			L <= 0;
			Z <= 0;
			P <= 0;
		end
	end
	
	always @ (*) begin
		NextState = CurrentState;
		case (CurrentState)
			STATE_Initial: begin 
				if (mul==1'b0) 
					NextState = STATE_Initial;
				else
					NextState = STATE_1;
			end
			STATE_1: begin
				NextState = STATE_2;
			end
			STATE_2: begin
				NextState = STATE_3;
			end
			STATE_3: begin 
				NextState = STATE_4;
			end
			STATE_4: begin
				NextState = STATE_Initial;
			end
			STATE_5: begin
				NextState = STATE_Initial;
			end
			STATE_6: begin
				NextState = STATE_Initial;
			end
			STATE_7: begin
				NextState = STATE_Initial;
			end
		endcase
	end
	
	always @ (*) begin 
		case (CurrentState)
			STATE_Initial: begin 
				H <= a_h * b_h;
				working <= mul;
				done <= 1'b0;
			end 
			STATE_1: begin 
				L <= a_l * b_l;
				working <= 1'b1;
			end 
			STATE_2 : begin 
				P <= (a_h+a_l)*(b_h+b_l);
				working <= 1'b1;
			end
			STATE_3 : begin 
				Z <= P - H - L;
				working <= 1'b1;
			end 
			STATE_4 : begin 
				result <= (Z<<32)+(Z<<16)+(L);
				working = 1'b0;
				done <= 1'b1;
			end 
		endcase
		
	end

endmodule

Pipeline_files/test/test_multiply.v
module testbench;

	reg clock;
	reg reset;
	reg mul;
	reg [0:31] a,b;
	wire [0:63] result;
	wire working,done;
	
	multiplier top(
		.clk(clock),
		.reset(reset),
		.mul(mul),
		.a(a),
		.b(b),
		.result(result),
		.done(done),
		.working(working)
	);
	
	always begin 
		#1 clock = ~clock;
	end 
	
	initial begin 
   	$dumpvars(0);

		#0 clock = 0; reset = 1; mul=0;
		a = 2; b=2;
		#2 reset = 0;
		#3 mul=1;
		#16;
		if (done==1'b1) begin 
			$display ("Done");
			$finish;
		end
		$finish;
	end 
	
	initial begin 
	
		$monitor ("clk=%b, reset=%b, mul=%b, a=%d, b=%d, result=%d, working=%b, done=%b, CurrentState=%d NextState=%d",clock,reset,mul,a,b,result,working,done,top.CurrentState,top.NextState);
	end 
endmodule

Pipeline_files/dump.vcd
$date
	Sat Mar 12 19:22:08 2016
$end
$version
	Icarus Verilog
$end
$timescale
	1s
$end
$scope module testbench $end
$var wire 1 ! working $end
$var wire 64 " result [0:63] $end
$var wire 1 # done $end
$var reg 32 $ a [0:31] $end
$var reg 32 % b [0:31] $end
$var reg 1 & clock $end
$var reg 1 ' mul $end
$var reg 1 ( reset $end
$scope module top $end
$var wire 32 ) a [0:31] $end
$var wire 32 * b [0:31] $end
$var wire 1 & clk $end
$var wire 1 ' mul $end
$var wire 1 ( reset $end
$var wire 16 + b_l [0:15] $end
$var wire 16 , b_h [0:15] $end
$var wire 16 - a_l [0:15] $end
$var wire 16 . a_h [0:15] $end
$var reg 3 / CurrentState [0:2] $end
$var reg 32 0 H [0:31] $end
$var reg 32 1 L [0:31] $end
$var reg 3 2 NextState [0:2] $end
$var reg 32 3 P [0:31] $end
$var reg 32 4 Z [0:31] $end
$var reg 1 # done $end
$var reg 64 5 result [0:63] $end
$var reg 1 ! working $end
$upscope $end
$upscope $end
$enddefinitions $end
#0
$dumpvars
b0 5
b0 4
b0 3
bx 2
b0 1
b0 0
bx /
b0 .
b10 -
b0 ,
b10 +
b10 *
b10 )
1(
0'
0&
b10 %
b10 $
x#
b0 "
x!
$end
#1
0#
0!
b0 2
b0 /
1&
#2
0&
0(
#3
1&
#4
0&
#5
b100 1
b1 /
1!
b10 2
1&
1'
#6
0&
#7
b100 3
b11 2
b10 /
1&
#8
0&
#9
b100 2
b11 /
1&
#10
0&
#11
1#
b100 "
b100 5
0!
b0 2
b100 /
1&
#12
0&
#13
0#
1!
b1 2
b0 /
1&
#14
0&
#15
b10 2
b1 /
1&
#16
0&
#17
b11 2
b10 /
1&
#18
0&
#19
b100 2
b11 /
1&
#20
0&
#21
1#
0!
b0 2
b100 /
1&
