Single_Cycle_files/src/control.v
module control(
    instruction, //input
    //PC Logic Controls
    PCtoReg, 
    regToPC, 
    jump, 
    branch,
    branchZero, 
    //Register Controls
    RType, //inclues all RType instructions, replaces RegDst and ALUSrc in Datapath
    RegWrite, //all RTypes are included, plus JAL, JALR, LB, LH, LW, LBU, LHU
    //Data Memory Controls
    DSize,
    MemToReg, //all loads
    MemWrite, //all stores
    //ALU/Execution Stage Controls
    ALUCtrl,
    mul,
    extOp, //0 for unsigned immediate instructions
    LHIOp //1 for LHI
);
    input [0:31] instruction;
    output PCtoReg, regToPC, jump, branch, branchZero, RType, RegWrite, MemToReg, MemWrite, mul, extOp, LHIOp;
    output [0:1] DSize;
    output [0:3] ALUCtrl;
    
    //NOTE: for I-type instructions, rd is located where rs2 is located for R-type instructions
    //This will simply be called rs2 for the purposes of our processor
    wire [0:5] opcode, func;
    wire [0:4] fpfunc;
    wire [0:4] rs1, rs2, rd;
    wire [0:15] imm16;
    wire [0:25] imm26;
    wire FPRType, jumpNotLink;
    assign opcode = instruction[0:5];
    assign func = instruction[26:31];
    assign fpfunc = instruction[27:31];
    assign rs1 = instruction[6:10];
    assign rs2 = instruction[11:15];
    assign rd = instruction[16:20];
    assign imm16 = instruction[16:31];
    assign imm26 = instruction[6:31];
    
    assign PCtoReg = (~opcode[0]) & (~opcode[2]) & (~opcode[3]) & opcode[4] & opcode[5];
    assign regToPC = (~opcode[0]) & opcode[1] & (~opcode[2]) & (~opcode[3]) & opcode[4];
    assign jump = (~opcode[0]) & (~opcode[2]) & (~opcode[3]) & opcode[4];
    assign branch = (~opcode[0]) & (~opcode[1]) & (~opcode[2]) & opcode[3] & (~opcode[4]);
    assign branchZero = branch & (~opcode[5]);
    assign jumpNotLink = jump & (~PCtoReg);
    assign RType = (~opcode[0]) & (~opcode[1]) & (~opcode[2]) & (~opcode[3]) & (~opcode[4]) & (~opcode[5]);
    assign FPRType = (~opcode[0]) & (~opcode[1]) & (~opcode[2]) & (~opcode[3]) & (~opcode[4]) & opcode[5];
    assign RegWrite = (~MemWrite) & (~jumpNotLink) & (~branch);
    assign MemToReg = opcode[0] & (~opcode[1]) & (~opcode[2]) & ((~opcode[4]) | ((~opcode[3]) & opcode[4] & opcode[5]));
    assign MemWrite = opcode[0] & (~opcode[1]) & opcode[2] & (~opcode[3]) & ((~opcode[4]) | (opcode[4] & opcode[5]));
    assign mul = FPRType & fpfunc[2] & fpfunc[3] & (~fpfunc[4]) & (fpfunc[0] ^ fpfunc[1]);
    assign extOp = opcode[0] & opcode[1] & (~opcode[2]) & opcode[3] & (~opcode[5]); //the opposite of the opcodes for ADDUI and SUBUI, so that it is zero for these operations
    assign LHIOp = (~opcode[0]) & (~opcode[1]) & opcode[2] & opcode[3] & opcode[4] & opcode[5];
    
    assign DSize[0] = opcode[0] & (~opcode[1]) & (~opcode[3]) & opcode[4] & opcode[5];
    assign DSize[1] = (opcode[0] & (~opcode[1]) & (~opcode[3]) & opcode[5]) | (opcode[0] & (~opcode[1]) & (~opcode[2]) & opcode[3] & (~opcode[4]) & opcode[5]);
    
    assign ALUCtrl[0] = 1'b1;
    assign ALUCtrl[1] = 1'b0;
    assign ALUCtrl[2] = 1'b1;
    assign ALUCtrl[3] = 1'b0;
    
endmodule

Single_Cycle_files/tests/control_test.v




//-------------
// File: control_test.v
// Purpose: Verilog Test Control Module  - Simulation
//--------------

module testbench;
	//declare signals
    reg [0:31] instruction;
    wire PCtoReg, regToPC, jump, branch, branchZero, RType, RegWrite, MemToReg, MemWrite, mul, extOp, LHIOp;
    wire [0:1] DSize;
    wire [0:3] ALUCtrl;
    
    reg [0:4] r1,r2,rd;
    reg [0:6] opcode;
    reg [0:15] imm16;
    reg [0:25] imm26;
    reg [0:5] func;
    reg [0:4] unused;

    //wire signals together
	control CTRL (
	    .instruction(instruction),
	    .PCtoReg(PCtoReg),
	    .regToPC(regToPC),
	    .jump(jump),
	    .branch(branch),
	    .branchZero(branchZero),
	    .RType(RType),
	    .RegWrite(RegWrite),
	    .MemToReg(MemToReg),
	    .MemWrite(MemWrite),
	    .mul(mul),
	    .extOp(extOp),
	    .LHIOp(LHIOp),
	    .DSize(DSize),
	    .ALUCtrl(ALUCtrl)
	);

	initial
	begin
	    $dumpfile("tests/test_control.vcd");
    	$dumpvars(0);
		//reset 
		
		unused = 6'd0;
		//start
// 		instruction = 32'h00000000;
		$display("Starting test ");
		$display("r-type instructions");
		#1;
		//r-type instruction
		$display("Add r3=r1+r2");
		opcode = 6'h0;
		func = 6'h20;
		r1=5'd1;
		r2=5'd2;
		rd=5'd3;
		instruction = {opcode,r1,r2,unused,func};
		#1;
		$display("Sub r3=r1-r2");
		func = 6'h22;
		instruction = {opcode,r1,r2,unused,func};
		#1;
		
		
		//immediate-type  (start with branching)
		
		$display("jump to imm26");
		opcode = 6'h2;
		imm26 = 26'h1919;
	    instruction = {opcode,imm26};
        #1;
		
		$display("jal ");
		opcode = 6'h3;
		instruction = {opcode,imm26};
		#1;
		
		$display("beqz");
		opcode = 6'h4;
		r1=5'h1;
		r2=5'h2;
		imm16=16'h23;
		instruction = {opcode,r1,r2,imm16};
		#1;
		
		$display("bnez");
		opcode = 6'h5;
		r1=5'h1;
		r2=5'h2;
		imm16=16'h23;
		instruction = {opcode,r1,r2,imm16};
		#1;
		
		$display("addi r5 = r1+Imm16");
		opcode = 6'h8;
		rd = 5'h5;
		instruction = {opcode,r1,rd,imm16};
		#1;
		
		$display("addui");
		opcode = 6'h9;
		instruction = {opcode,r1,rd,imm16};
		#1;
		
		$display("subi");
		opcode = 6'ha;
		instruction = {opcode,r1,rd,imm16};
		#1;
		
		$display("subui");
		opcode = 6'hb;
		instruction = {opcode,r1,rd,imm16};
		#1;
		
		$display("andi");
		opcode = 6'hc;
		instruction = {opcode,r1,rd,imm16};
		#1;
		
		$display("ori");
		opcode = 6'hd;
		instruction = {opcode,r1,rd,imm16};
		#1;
		
		$display("xori");
		opcode = 6'he;
		instruction = {opcode,r1,rd,imm16};
		#1;
		
		
		
		
		
		//load and store instructions
		$display("\n ----- LOAD AND STORE ");
		$display("lb");
		opcode = 6'h20;
		r1 = 5'h1;
		rd = 5'h2;
		imm16 = 16'h29;
		instruction = {opcode,r1,rd,imm16};
		#1;
		
		$display("lh");
		opcode = 6'h21;
		r1 = 5'h1;
		rd = 5'h2;
		imm16 = 16'h29;
		instruction = {opcode,r1,rd,imm16};
		#1;
		
		$display("lw");
		opcode = 6'h23;
		r1 = 5'h1;
		rd = 5'h2;
		imm16 = 16'h29;
		instruction = {opcode,r1,rd,imm16};
		#1;
		
		$display("lbu");
		opcode = 6'h24;
		r1 = 5'h1;
		rd = 5'h2;
		imm16 = 16'h29;
		instruction = {opcode,r1,rd,imm16};
		#1;
		
		$display("lhu");
		opcode = 6'h25;
		r1 = 5'h1;
		rd = 5'h2;
		imm16 = 16'h29;
		instruction = {opcode,r1,rd,imm16};
		#1;
		
		$display("sb");
		opcode = 6'h28;
		r1 = 5'h1;
		rd = 5'h2;
		imm16 = 16'h29;
		instruction = {opcode,r1,rd,imm16};
		#1;
		
		$display("sh");
		opcode = 6'h29;
		r1 = 5'h1;
		rd = 5'h2;
		imm16 = 16'h29;
		instruction = {opcode,r1,rd,imm16};
		#1;
		
		$display("sw");
		opcode = 6'h2b;
		r1 = 5'h1;
		rd = 5'h2;
		imm16 = 16'h29;
		instruction = {opcode,r1,rd,imm16};
		#1;
		

		$finish;
	end

	initial
	begin
	//PCtoReg, regToPC, jump, branch, branchZero, RType, RegWrite, MemToReg, MemWrite, mul, extOp, LHIOp
		$monitor("Instruction=%x, PCtoReg=%x regToPC=%x jump=%x branch=%x branchZero=%x RType=%x RegWrite=%x MemToReg=%x MemWrite=%x mul=%x extOp=%x LHIOp=%x Dsize=%x ALUCtrl=%x",
		        instruction, PCtoReg,regToPC,jump,branch,branchZero,RType,RegWrite,MemToReg,MemWrite,mul,extOp,LHIOp,DSize,ALUCtrl);
	end
endmodule

Single_Cycle_files/tests/test_control.vcd
$date
	Mon Feb 15 20:15:31 2016
$end
$version
	Icarus Verilog
$end
$timescale
	1s
$end
$scope module testbench $end
$var wire 1 ! regToPC $end
$var wire 1 " mul $end
$var wire 1 # jump $end
$var wire 1 $ extOp $end
$var wire 1 % branchZero $end
$var wire 1 & branch $end
$var wire 1 ' RegWrite $end
$var wire 1 ( RType $end
$var wire 1 ) PCtoReg $end
$var wire 1 * MemWrite $end
$var wire 1 + MemToReg $end
$var wire 1 , LHIOp $end
$var wire 2 - DSize [0:1] $end
$var wire 4 . ALUCtrl [0:3] $end
$var reg 6 / func [0:5] $end
$var reg 16 0 imm16 [0:15] $end
$var reg 26 1 imm26 [0:25] $end
$var reg 32 2 instruction [0:31] $end
$var reg 7 3 opcode [0:6] $end
$var reg 5 4 r1 [0:4] $end
$var reg 5 5 r2 [0:4] $end
$var reg 5 6 rd [0:4] $end
$var reg 5 7 unused [0:4] $end
$scope module CTRL $end
$var wire 1 8 FPRType $end
$var wire 1 , LHIOp $end
$var wire 1 + MemToReg $end
$var wire 1 * MemWrite $end
$var wire 1 ) PCtoReg $end
$var wire 1 ( RType $end
$var wire 1 ' RegWrite $end
$var wire 1 & branch $end
$var wire 1 % branchZero $end
$var wire 1 $ extOp $end
$var wire 32 9 instruction [0:31] $end
$var wire 1 # jump $end
$var wire 1 : jumpNotLink $end
$var wire 1 " mul $end
$var wire 1 ! regToPC $end
$var wire 5 ; rs2 [0:4] $end
$var wire 5 < rs1 [0:4] $end
$var wire 5 = rd [0:4] $end
$var wire 6 > opcode [0:5] $end
$var wire 26 ? imm26 [0:25] $end
$var wire 16 @ imm16 [0:15] $end
$var wire 6 A func [0:5] $end
$var wire 5 B fpfunc [0:4] $end
$var wire 2 C DSize [0:1] $end
$var wire 4 D ALUCtrl [0:3] $end
$upscope $end
$upscope $end
$enddefinitions $end
#0
$dumpvars
b1010 D
bx C
bx B
bx A
bx @
bx ?
bx >
bx =
bx <
bx ;
x:
bx 9
x8
b0 7
bx 6
bx 5
bx 4
bx 3
bx 2
bx 1
bx 0
bx /
b1010 .
bx -
x,
x+
x*
x)
x(
x'
x&
x%
x$
x#
x"
x!
$end
#1
1(
1'
0%
0+
0*
0:
0&
0$
0"
0)
0!
0#
08
0,
b0 -
b0 C
b0 >
b100000 A
b0 B
b0 <
b1 ;
b10 =
b1000000100000 @
b10001000000100000 ?
b10001000000100000 2
b10001000000100000 9
b11 6
b10 5
b1 4
b100000 /
b0 3
#2
b100010 A
b10 B
b1000000100010 @
b10001000000100010 ?
b10001000000100010 2
b10001000000100010 9
b100010 /
#3
0'
0(
1:
1#
b10 >
b11001 A
b11001 B
b0 ;
b11 =
b1100100011001 @
b1100100011001 ?
b1000000000000001100100011001 2
b1000000000000001100100011001 9
b1100100011001 1
b10 3
#4
1'
0:
1)
b11 >
b1100000000000001100100011001 2
b1100000000000001100100011001 9
b11 3
#5
0'
1%
0(
1&
0)
0#
b100 >
b100011 A
b11 B
b1 <
b10 ;
b0 =
b100011 @
b1000100000000000100011 ?
b10000001000100000000000100011 2
b10000001000100000000000100011 9
b100011 0
b100 3
#6
0%
b101 >
b10100001000100000000000100011 2
b10100001000100000000000100011 9
b101 3
#7
1'
0(
0&
0%
b1000 >
b101 ;
b1001010000000000100011 ?
b100000001001010000000000100011 2
b100000001001010000000000100011 9
b101 6
b1000 3
#8
b1001 >
b100100001001010000000000100011 2
b100100001001010000000000100011 9
b1001 3
#9
b1010 >
b101000001001010000000000100011 2
b101000001001010000000000100011 9
b1010 3
#10
b1011 >
b101100001001010000000000100011 2
b101100001001010000000000100011 9
b1011 3
#11
b1100 >
b110000001001010000000000100011 2
b110000001001010000000000100011 9
b1100 3
#12
b1101 >
b110100001001010000000000100011 2
b110100001001010000000000100011 9
b1101 3
#13
b1110 >
b111000001001010000000000100011 2
b111000001001010000000000100011 9
b1110 3
#14
0(
1+
b100000 >
b101001 A
b1001 B
b10 ;
b101001 @
b1000100000000000101001 ?
b10000000001000100000000000101001 2
b10000000001000100000000000101001 9
b101001 0
b10 6
b100000 3
#15
b1 -
b1 C
b100001 >
b10000100001000100000000000101001 2
b10000100001000100000000000101001 9
b100001 3
#16
b11 -
b11 C
b100011 >
b10001100001000100000000000101001 2
b10001100001000100000000000101001 9
b100011 3
#17
b0 -
b0 C
b100100 >
b10010000001000100000000000101001 2
b10010000001000100000000000101001 9
b100100 3
#18
b1 -
b1 C
b100101 >
b10010100001000100000000000101001 2
b10010100001000100000000000101001 9
b100101 3
#19
0'
0+
1*
b0 -
b0 C
b101000 >
b10100000001000100000000000101001 2
b10100000001000100000000000101001 9
b101000 3
#20
b1 -
b1 C
b101001 >
b10100100001000100000000000101001 2
b10100100001000100000000000101001 9
b101001 3
#21
b11 -
b11 C
b101011 >
b10101100001000100000000000101001 2
b10101100001000100000000000101001 9
b101011 3
